.gitattributes
AUTHORS.rst
CHANGES.rst
LICENSE.txt
MANIFEST.in
README.rst
README.rst~
requirements.txt
setup.cfg
setup.py
test-requirements.txt
versioneer.py
keyinfo/__init__.py
keyinfo/_version.py
keyinfo/keyinfo.py
keyinfo.egg-info/PKG-INFO
keyinfo.egg-info/SOURCES.txt
keyinfo.egg-info/dependency_links.txt
keyinfo.egg-info/not-zip-safe
keyinfo.egg-info/requires.txt
keyinfo.egg-info/top_level.txt
tests/test_keyinfo.py
tests/data/ca_A_CA_keyinfo_sig11.xml
tests/data/party_P1_signing_keyinfo.xml
tests/data/party_P1_signing_keyinfo_bad_issuer.xml
tests/data/party_P1_signing_keyinfo_bad_serial.xml
tests/data/party_P1_signing_keyinfo_sig11.xml
tests/data/party_P1_signing_keyinfo_sig11_bad_digest.xml
tests/data/party_P2_signing_certificate.pem