Metadata-Version: 1.1
Name: keyinfo
Version: 0.9.1
Summary: Python library to convert X.509 certificates to and from W3C XML Signature KeyInfo structures
Home-page: http://...
Author: Pim van der Eijk, Ernst Jan van Nigtevecht
Author-email: pvde@sonnenglanz.net, ejvn@sonnenglanz.net
License: mit
Platform: UNKNOWN
Classifier: Development Status :: 4 - Beta
Classifier: Programming Language :: Python
